phu/__init__.py
phu/_exec.py
phu/cli.py
phu/cluster.py
phu/screen.py
phu/simplify_vcontact_taxa.py
phu-0.4.4.dist-info/licenses/LICENSE
phu-0.4.4.dist-info/METADATA
phu-0.4.4.dist-info/WHEEL
phu-0.4.4.dist-info/entry_points.txt
phu-0.4.4.dist-info/top_level.txt
phu-0.4.4.dist-info/RECORD
