Metadata-Version: 2.4
Name: phu
Version: 0.4.4
Summary: Phage bioinformatics utilities (seqclust runner and friends).
Author-email: Camilo García-Botero <ca.garcia2@uniandes.edu.co>
License: MIT
Requires-Python: >=3.10
License-File: LICENSE
Requires-Dist: pandas>=2.3.2
Requires-Dist: pyhmmer>=0.11.1
Requires-Dist: pyrodigal>=3.6.3.post1
Requires-Dist: pyrodigal-gv>=0.3.2
Requires-Dist: typer>=0.17.3
Dynamic: license-file
